tmstr/Date.py
tmstr/Range.py
tmstr/__init__.py
tmstr/text2num.py
tmstr/time_regex.py
tmstr-0.0.1.dist-info/METADATA
tmstr-0.0.1.dist-info/WHEEL
tmstr-0.0.1.dist-info/top_level.txt
tmstr-0.0.1.dist-info/RECORD
