Metadata-Version: 2.4
Name: tmstr
Version: 0.0.1
Summary: Turning stuff into times since Jan 17th, 2013 at 3:59pm
Author-email: Steve Peak <hello@codecov.io>, Jason Wilkes <notarealdeveloper@gmail.com>
Project-URL: source, https://github.com/notarealdeveloper/tmstr
Requires-Dist: pytz
Provides-Extra: develop
Requires-Dist: build; extra == "develop"
Requires-Dist: pytest; extra == "develop"
